mongolia/__init__.py
mongolia/constants.py
mongolia/database_collection.py
mongolia/database_object.py
mongolia/errors.py
mongolia/json_codecs.py
mongolia/mongo_connection.py
mongolia/testing.py
mongolia-0.7.0.dist-info/licenses/LICENSE
mongolia-0.7.0.dist-info/METADATA
mongolia-0.7.0.dist-info/WHEEL
mongolia-0.7.0.dist-info/top_level.txt
mongolia-0.7.0.dist-info/RECORD
