Metadata-Version: 2.4
Name: mongolia
Version: 0.7.0
Summary: An interface between mongodb and basic python data structures
Author-email: "Zagaran, Inc." <info@zagaran.com>
License-Expression: MIT
Project-URL: Homepage, https://github.com/zagaran/mongolia
Keywords: mongo,mongodb,database,python,interface,dictionary,collection
Classifier: Development Status :: 4 - Beta
Classifier: Operating System :: MacOS :: MacOS X
Classifier: Operating System :: Microsoft :: Windows
Classifier: Operating System :: POSIX
Classifier: Programming Language :: Python
Classifier: Topic :: Database
Requires-Python: >=3.6
License-File: LICENSE
Requires-Dist: pymongo>=3.0
Requires-Dist: python-dateutil>=2.6.0
Dynamic: license-file
